{
  "schema_version": 1,
  "as_of": "2026-05-23",
  "generated_at": "2026-05-24T07:39:19.635323+00:00",
  "account_id": "main",
  "env": "paper",
  "strategy": "nasdaq_momentum_top10",
  "cash": 1234.56,
  "equity": 10000.0,
  "holdings": [
    {
      "symbol": "AAPL",
      "qty": 10,
      "market_value": 1600.0,
      "returns": {
        "1d": 0.01,
        "1w": 0.03,
        "1m": 0.08
      },
      "pe_ratio": 30.5
    },
    {
      "symbol": "NVDA",
      "qty": 3,
      "market_value": 2400.0,
      "returns": {
        "1d": 0.02,
        "1w": -0.01,
        "1m": 0.15
      },
      "pe_ratio": 60.0
    }
  ],
  "top10": [
    {
      "rank": 1,
      "symbol": "NVDA",
      "score": 0.3
    },
    {
      "rank": 2,
      "symbol": "AAPL",
      "score": 0.27999999999999997
    },
    {
      "rank": 3,
      "symbol": "MSFT",
      "score": 0.26
    },
    {
      "rank": 4,
      "symbol": "AVGO",
      "score": 0.24
    },
    {
      "rank": 5,
      "symbol": "META",
      "score": 0.21999999999999997
    },
    {
      "rank": 6,
      "symbol": "AMD",
      "score": 0.19999999999999998
    },
    {
      "rank": 7,
      "symbol": "GOOGL",
      "score": 0.18
    },
    {
      "rank": 8,
      "symbol": "TSLA",
      "score": 0.15999999999999998
    },
    {
      "rank": 9,
      "symbol": "COST",
      "score": 0.13999999999999999
    },
    {
      "rank": 10,
      "symbol": "NFLX",
      "score": 0.12
    }
  ],
  "next_day_candidates": {
    "note": "依動能等因子排名的研究參考清單，非股價預測，不構成投資建議。",
    "items": [
      {
        "symbol": "NVDA",
        "score": 0.28
      },
      {
        "symbol": "AVGO",
        "score": 0.22
      }
    ]
  },
  "watch_categories": [
    {
      "name": "半導體",
      "symbols": [
        {
          "symbol": "NVDA",
          "pe_ratio": 60.0
        },
        {
          "symbol": "AVGO",
          "pe_ratio": 35.0
        }
      ]
    },
    {
      "name": "雲端軟體",
      "symbols": [
        {
          "symbol": "MSFT",
          "pe_ratio": 35.0
        }
      ]
    },
    {
      "name": "電動車",
      "symbols": [
        {
          "symbol": "TSLA",
          "pe_ratio": 70.0
        }
      ]
    }
  ],
  "nav": {
    "dates": [
      "2026-05-19",
      "2026-05-20",
      "2026-05-21",
      "2026-05-22",
      "2026-05-23"
    ],
    "portfolio": [
      100.0,
      102.10526315789474,
      101.05263157894737,
      103.68421052631578,
      105.26315789473684
    ],
    "nasdaq": [
      100.0,
      100.27777777777777,
      99.44444444444444,
      100.83333333333333,
      101.11111111111111
    ],
    "sp500": [
      100.0,
      100.09615384615384,
      99.61538461538461,
      100.38461538461539,
      100.57692307692308
    ]
  },
  "drawdown": {
    "dates": [
      "2026-05-19",
      "2026-05-20",
      "2026-05-21",
      "2026-05-22",
      "2026-05-23"
    ],
    "portfolio": [
      0.0,
      0.0,
      -0.010309278350515427,
      0.0,
      0.0
    ],
    "nasdaq": [
      0.0,
      0.0,
      -0.008310249307479145,
      0.0,
      0.0
    ],
    "sp500": [
      0.0,
      0.0,
      -0.004803073967339033,
      0.0,
      0.0
    ],
    "portfolio_max_drawdown": -0.010309278350515427
  },
  "rebalance": {
    "triggered": true,
    "reason": "monthly_first_trading_day"
  },
  "trades": [],
  "disclaimer": "本內容僅供資訊整理與研究參考，不構成投資建議。投資有風險，請自行評估。"
}